entry/__init__.py
entry/client.py
entry/enums.py
entry/object.py
entry/post.py
entry/project.py
entry/user.py
entry/utils.py
playentry-0.0.11.dist-info/LICENSE
playentry-0.0.11.dist-info/METADATA
playentry-0.0.11.dist-info/WHEEL
playentry-0.0.11.dist-info/top_level.txt
playentry-0.0.11.dist-info/RECORD
